fbgemm_gpu/__init__.py
fbgemm_gpu/asmjit.so
fbgemm_gpu/batched_unary_embeddings_ops.py
fbgemm_gpu/enums.py
fbgemm_gpu/fbgemm.so
fbgemm_gpu/metrics.py
fbgemm_gpu/permute_pooled_embedding_modules.py
fbgemm_gpu/permute_pooled_embedding_modules_split.py
fbgemm_gpu/quantize_comm.py
fbgemm_gpu/quantize_utils.py
fbgemm_gpu/runtime_monitor.py
fbgemm_gpu/sparse_ops.py
fbgemm_gpu/split_embedding_configs.py
fbgemm_gpu/split_embedding_inference_converter.py
fbgemm_gpu/split_embedding_optimizer_ops.py
fbgemm_gpu/split_embedding_utils.py
fbgemm_gpu/split_table_batched_embeddings_ops.py
fbgemm_gpu/split_table_batched_embeddings_ops_common.py
fbgemm_gpu/split_table_batched_embeddings_ops_inference.py
fbgemm_gpu/split_table_batched_embeddings_ops_training.py
fbgemm_gpu/split_table_batched_embeddings_ops_training_common.py
fbgemm_gpu/ssd_split_table_batched_embeddings_ops.py
fbgemm_gpu/tbe_input_multiplexer.py
fbgemm_gpu/uvm.py
fbgemm_gpu/config/__init__.py
fbgemm_gpu/config/feature_list.py
fbgemm_gpu/docs/__init__.py
fbgemm_gpu/docs/common.py
fbgemm_gpu/docs/examples.py
fbgemm_gpu/docs/jagged_tensor_ops.py
fbgemm_gpu/docs/merge_pooled_embedding_ops.py
fbgemm_gpu/docs/permute_pooled_embedding_ops.py
fbgemm_gpu/docs/quantize_ops.py
fbgemm_gpu/docs/sparse_ops.py
fbgemm_gpu/docs/target.genai.json.py
fbgemm_gpu/experimental/example/__init__.py
fbgemm_gpu/experimental/example/fbgemm_gpu_experimental_example_py.so
fbgemm_gpu/experimental/example/utils.py
fbgemm_gpu/experimental/gemm/triton_gemm/__init__.py
fbgemm_gpu/experimental/gemm/triton_gemm/fp4_quantize.py
fbgemm_gpu/experimental/gemm/triton_gemm/fp8_gemm.py
fbgemm_gpu/experimental/gemm/triton_gemm/grouped_gemm.py
fbgemm_gpu/experimental/gemm/triton_gemm/matmul_perf_model.py
fbgemm_gpu/experimental/gemm/triton_gemm/utils.py
fbgemm_gpu/experimental/gen_ai/__init__.py
fbgemm_gpu/experimental/gen_ai/fbgemm_gpu_experimental_gen_ai.so
fbgemm_gpu/experimental/gen_ai/quantize.py
fbgemm_gpu_genai_nightly-2026.2.1.dist-info/METADATA
fbgemm_gpu_genai_nightly-2026.2.1.dist-info/WHEEL
fbgemm_gpu_genai_nightly-2026.2.1.dist-info/top_level.txt
fbgemm_gpu_genai_nightly-2026.2.1.dist-info/RECORD
